<?xml version="1.0" encoding="utf-8"?>
<resources>
	<dimen name="_1ssp">0.00sp</dimen>
	<dimen name="_2ssp">0.00sp</dimen>
	<dimen name="_3ssp">0.00sp</dimen>
	<dimen name="_4ssp">0.00sp</dimen>
	<dimen name="_5ssp">0.00sp</dimen>
	<dimen name="_6ssp">0.00sp</dimen>
	<dimen name="_7ssp">0.00sp</dimen>
	<dimen name="_8ssp">0.00sp</dimen>
	<dimen name="_9ssp">0.00sp</dimen>
	<dimen name="_10ssp">0.00sp</dimen>
	<dimen name="_11ssp">0.00sp</dimen>
	<dimen name="_12ssp">0.00sp</dimen>
	<dimen name="_13ssp">0.00sp</dimen>
	<dimen name="_14ssp">0.00sp</dimen>
	<dimen name="_15ssp">0.00sp</dimen>
	<dimen name="_16ssp">0.00sp</dimen>
	<dimen name="_17ssp">0.00sp</dimen>
	<dimen name="_18ssp">0.00sp</dimen>
	<dimen name="_19ssp">0.00sp</dimen>
	<dimen name="_20ssp">0.00sp</dimen>
	<dimen name="_21ssp">0.00sp</dimen>
	<dimen name="_22ssp">0.00sp</dimen>
	<dimen name="_23ssp">0.00sp</dimen>
	<dimen name="_24ssp">0.00sp</dimen>
	<dimen name="_25ssp">0.00sp</dimen>
	<dimen name="_26ssp">0.00sp</dimen>
	<dimen name="_27ssp">0.00sp</dimen>
	<dimen name="_28ssp">0.00sp</dimen>
	<dimen name="_29ssp">0.00sp</dimen>
	<dimen name="_30ssp">0.00sp</dimen>
	<dimen name="_31ssp">0.00sp</dimen>
	<dimen name="_32ssp">0.00sp</dimen>
	<dimen name="_33ssp">0.00sp</dimen>
	<dimen name="_34ssp">0.00sp</dimen>
	<dimen name="_35ssp">0.00sp</dimen>
	<dimen name="_36ssp">0.00sp</dimen>
	<dimen name="_37ssp">0.00sp</dimen>
	<dimen name="_38ssp">0.00sp</dimen>
	<dimen name="_39ssp">0.00sp</dimen>
	<dimen name="_40ssp">0.00sp</dimen>
	<dimen name="_41ssp">0.00sp</dimen>
	<dimen name="_42ssp">0.00sp</dimen>
	<dimen name="_43ssp">0.00sp</dimen>
	<dimen name="_44ssp">0.00sp</dimen>
	<dimen name="_45ssp">0.00sp</dimen>
	<dimen name="_46ssp">0.00sp</dimen>
	<dimen name="_47ssp">0.00sp</dimen>
	<dimen name="_48ssp">0.00sp</dimen>
	<dimen name="_49ssp">0.00sp</dimen>
	<dimen name="_50ssp">0.00sp</dimen>
	<dimen name="_51ssp">0.00sp</dimen>
	<dimen name="_52ssp">0.00sp</dimen>
	<dimen name="_53ssp">0.00sp</dimen>
	<dimen name="_54ssp">0.00sp</dimen>
	<dimen name="_55ssp">0.00sp</dimen>
	<dimen name="_56ssp">0.00sp</dimen>
	<dimen name="_57ssp">0.00sp</dimen>
	<dimen name="_58ssp">0.00sp</dimen>
	<dimen name="_59ssp">0.00sp</dimen>
	<dimen name="_60ssp">0.00sp</dimen>
	<dimen name="_61ssp">0.00sp</dimen>
	<dimen name="_62ssp">0.00sp</dimen>
	<dimen name="_63ssp">0.00sp</dimen>
	<dimen name="_64ssp">0.00sp</dimen>
	<dimen name="_65ssp">0.00sp</dimen>
	<dimen name="_66ssp">0.00sp</dimen>
	<dimen name="_67ssp">0.00sp</dimen>
	<dimen name="_68ssp">0.00sp</dimen>
	<dimen name="_69ssp">0.00sp</dimen>
	<dimen name="_70ssp">0.00sp</dimen>
	<dimen name="_71ssp">0.00sp</dimen>
	<dimen name="_72ssp">0.00sp</dimen>
	<dimen name="_73ssp">0.00sp</dimen>
	<dimen name="_74ssp">0.00sp</dimen>
	<dimen name="_75ssp">0.00sp</dimen>
	<dimen name="_76ssp">0.00sp</dimen>
	<dimen name="_77ssp">0.00sp</dimen>
	<dimen name="_78ssp">0.00sp</dimen>
	<dimen name="_79ssp">0.00sp</dimen>
	<dimen name="_80ssp">0.00sp</dimen>
	<dimen name="_81ssp">0.00sp</dimen>
	<dimen name="_82ssp">0.00sp</dimen>
	<dimen name="_83ssp">0.00sp</dimen>
	<dimen name="_84ssp">0.00sp</dimen>
	<dimen name="_85ssp">0.00sp</dimen>
	<dimen name="_86ssp">0.00sp</dimen>
	<dimen name="_87ssp">0.00sp</dimen>
	<dimen name="_88ssp">0.00sp</dimen>
	<dimen name="_89ssp">0.00sp</dimen>
	<dimen name="_90ssp">0.00sp</dimen>
	<dimen name="_91ssp">0.00sp</dimen>
	<dimen name="_92ssp">0.00sp</dimen>
	<dimen name="_93ssp">0.00sp</dimen>
	<dimen name="_94ssp">0.00sp</dimen>
	<dimen name="_95ssp">0.00sp</dimen>
	<dimen name="_96ssp">0.00sp</dimen>
	<dimen name="_97ssp">0.00sp</dimen>
	<dimen name="_98ssp">0.00sp</dimen>
	<dimen name="_99ssp">0.00sp</dimen>
	<dimen name="_100ssp">0.00sp</dimen>
</resources>
