<?xml version="1.0" encoding="utf-8"?>
<resources>
	<dimen name="_1sdp">1.09dp</dimen>
	<dimen name="_2sdp">2.19dp</dimen>
	<dimen name="_3sdp">3.28dp</dimen>
	<dimen name="_4sdp">4.38dp</dimen>
	<dimen name="_5sdp">5.47dp</dimen>
	<dimen name="_6sdp">6.56dp</dimen>
	<dimen name="_7sdp">7.66dp</dimen>
	<dimen name="_8sdp">8.75dp</dimen>
	<dimen name="_9sdp">9.84dp</dimen>
	<dimen name="_10sdp">10.94dp</dimen>
	<dimen name="_11sdp">12.03dp</dimen>
	<dimen name="_12sdp">13.13dp</dimen>
	<dimen name="_13sdp">14.22dp</dimen>
	<dimen name="_14sdp">15.31dp</dimen>
	<dimen name="_15sdp">16.41dp</dimen>
	<dimen name="_16sdp">17.50dp</dimen>
	<dimen name="_17sdp">18.59dp</dimen>
	<dimen name="_18sdp">19.69dp</dimen>
	<dimen name="_19sdp">20.78dp</dimen>
	<dimen name="_20sdp">21.88dp</dimen>
	<dimen name="_21sdp">22.97dp</dimen>
	<dimen name="_22sdp">24.06dp</dimen>
	<dimen name="_23sdp">25.16dp</dimen>
	<dimen name="_24sdp">26.25dp</dimen>
	<dimen name="_25sdp">27.34dp</dimen>
	<dimen name="_26sdp">28.44dp</dimen>
	<dimen name="_27sdp">29.53dp</dimen>
	<dimen name="_28sdp">30.62dp</dimen>
	<dimen name="_29sdp">31.72dp</dimen>
	<dimen name="_30sdp">32.81dp</dimen>
	<dimen name="_31sdp">33.91dp</dimen>
	<dimen name="_32sdp">35.00dp</dimen>
	<dimen name="_33sdp">36.09dp</dimen>
	<dimen name="_34sdp">37.19dp</dimen>
	<dimen name="_35sdp">38.28dp</dimen>
	<dimen name="_36sdp">39.38dp</dimen>
	<dimen name="_37sdp">40.47dp</dimen>
	<dimen name="_38sdp">41.56dp</dimen>
	<dimen name="_39sdp">42.66dp</dimen>
	<dimen name="_40sdp">43.75dp</dimen>
	<dimen name="_41sdp">44.84dp</dimen>
	<dimen name="_42sdp">45.94dp</dimen>
	<dimen name="_43sdp">47.03dp</dimen>
	<dimen name="_44sdp">48.13dp</dimen>
	<dimen name="_45sdp">49.22dp</dimen>
	<dimen name="_46sdp">50.31dp</dimen>
	<dimen name="_47sdp">51.41dp</dimen>
	<dimen name="_48sdp">52.50dp</dimen>
	<dimen name="_49sdp">53.59dp</dimen>
	<dimen name="_50sdp">54.69dp</dimen>
	<dimen name="_51sdp">55.78dp</dimen>
	<dimen name="_52sdp">56.88dp</dimen>
	<dimen name="_53sdp">57.97dp</dimen>
	<dimen name="_54sdp">59.06dp</dimen>
	<dimen name="_55sdp">60.16dp</dimen>
	<dimen name="_56sdp">61.25dp</dimen>
	<dimen name="_57sdp">62.34dp</dimen>
	<dimen name="_58sdp">63.44dp</dimen>
	<dimen name="_59sdp">64.53dp</dimen>
	<dimen name="_60sdp">65.63dp</dimen>
	<dimen name="_61sdp">66.72dp</dimen>
	<dimen name="_62sdp">67.81dp</dimen>
	<dimen name="_63sdp">68.91dp</dimen>
	<dimen name="_64sdp">70.00dp</dimen>
	<dimen name="_65sdp">71.09dp</dimen>
	<dimen name="_66sdp">72.19dp</dimen>
	<dimen name="_67sdp">73.28dp</dimen>
	<dimen name="_68sdp">74.38dp</dimen>
	<dimen name="_69sdp">75.47dp</dimen>
	<dimen name="_70sdp">76.56dp</dimen>
	<dimen name="_71sdp">77.66dp</dimen>
	<dimen name="_72sdp">78.75dp</dimen>
	<dimen name="_73sdp">79.84dp</dimen>
	<dimen name="_74sdp">80.94dp</dimen>
	<dimen name="_75sdp">82.03dp</dimen>
	<dimen name="_76sdp">83.13dp</dimen>
	<dimen name="_77sdp">84.22dp</dimen>
	<dimen name="_78sdp">85.31dp</dimen>
	<dimen name="_79sdp">86.41dp</dimen>
	<dimen name="_80sdp">87.50dp</dimen>
	<dimen name="_81sdp">88.59dp</dimen>
	<dimen name="_82sdp">89.69dp</dimen>
	<dimen name="_83sdp">90.78dp</dimen>
	<dimen name="_84sdp">91.88dp</dimen>
	<dimen name="_85sdp">92.97dp</dimen>
	<dimen name="_86sdp">94.06dp</dimen>
	<dimen name="_87sdp">95.16dp</dimen>
	<dimen name="_88sdp">96.25dp</dimen>
	<dimen name="_89sdp">97.34dp</dimen>
	<dimen name="_90sdp">98.44dp</dimen>
	<dimen name="_91sdp">99.53dp</dimen>
	<dimen name="_92sdp">100.62dp</dimen>
	<dimen name="_93sdp">101.72dp</dimen>
	<dimen name="_94sdp">102.81dp</dimen>
	<dimen name="_95sdp">103.91dp</dimen>
	<dimen name="_96sdp">105.00dp</dimen>
	<dimen name="_97sdp">106.09dp</dimen>
	<dimen name="_98sdp">107.19dp</dimen>
	<dimen name="_99sdp">108.28dp</dimen>
	<dimen name="_100sdp">109.38dp</dimen>
	<dimen name="_101sdp">110.47dp</dimen>
	<dimen name="_102sdp">111.56dp</dimen>
	<dimen name="_103sdp">112.66dp</dimen>
	<dimen name="_104sdp">113.75dp</dimen>
	<dimen name="_105sdp">114.84dp</dimen>
	<dimen name="_106sdp">115.94dp</dimen>
	<dimen name="_107sdp">117.03dp</dimen>
	<dimen name="_108sdp">118.13dp</dimen>
	<dimen name="_109sdp">119.22dp</dimen>
	<dimen name="_110sdp">120.31dp</dimen>
	<dimen name="_111sdp">121.41dp</dimen>
	<dimen name="_112sdp">122.50dp</dimen>
	<dimen name="_113sdp">123.59dp</dimen>
	<dimen name="_114sdp">124.69dp</dimen>
	<dimen name="_115sdp">125.78dp</dimen>
	<dimen name="_116sdp">126.88dp</dimen>
	<dimen name="_117sdp">127.97dp</dimen>
	<dimen name="_118sdp">129.06dp</dimen>
	<dimen name="_119sdp">130.16dp</dimen>
	<dimen name="_120sdp">131.25dp</dimen>
	<dimen name="_121sdp">132.34dp</dimen>
	<dimen name="_122sdp">133.44dp</dimen>
	<dimen name="_123sdp">134.53dp</dimen>
	<dimen name="_124sdp">135.63dp</dimen>
	<dimen name="_125sdp">136.72dp</dimen>
	<dimen name="_126sdp">137.81dp</dimen>
	<dimen name="_127sdp">138.91dp</dimen>
	<dimen name="_128sdp">140.00dp</dimen>
	<dimen name="_129sdp">141.09dp</dimen>
	<dimen name="_130sdp">142.19dp</dimen>
	<dimen name="_131sdp">143.28dp</dimen>
	<dimen name="_132sdp">144.38dp</dimen>
	<dimen name="_133sdp">145.47dp</dimen>
	<dimen name="_134sdp">146.56dp</dimen>
	<dimen name="_135sdp">147.66dp</dimen>
	<dimen name="_136sdp">148.75dp</dimen>
	<dimen name="_137sdp">149.84dp</dimen>
	<dimen name="_138sdp">150.94dp</dimen>
	<dimen name="_139sdp">152.03dp</dimen>
	<dimen name="_140sdp">153.13dp</dimen>
	<dimen name="_141sdp">154.22dp</dimen>
	<dimen name="_142sdp">155.31dp</dimen>
	<dimen name="_143sdp">156.41dp</dimen>
	<dimen name="_144sdp">157.50dp</dimen>
	<dimen name="_145sdp">158.59dp</dimen>
	<dimen name="_146sdp">159.69dp</dimen>
	<dimen name="_147sdp">160.78dp</dimen>
	<dimen name="_148sdp">161.88dp</dimen>
	<dimen name="_149sdp">162.97dp</dimen>
	<dimen name="_150sdp">164.06dp</dimen>
	<dimen name="_151sdp">165.16dp</dimen>
	<dimen name="_152sdp">166.25dp</dimen>
	<dimen name="_153sdp">167.34dp</dimen>
	<dimen name="_154sdp">168.44dp</dimen>
	<dimen name="_155sdp">169.53dp</dimen>
	<dimen name="_156sdp">170.63dp</dimen>
	<dimen name="_157sdp">171.72dp</dimen>
	<dimen name="_158sdp">172.81dp</dimen>
	<dimen name="_159sdp">173.91dp</dimen>
	<dimen name="_160sdp">175.00dp</dimen>
	<dimen name="_161sdp">176.09dp</dimen>
	<dimen name="_162sdp">177.19dp</dimen>
	<dimen name="_163sdp">178.28dp</dimen>
	<dimen name="_164sdp">179.37dp</dimen>
	<dimen name="_165sdp">180.47dp</dimen>
	<dimen name="_166sdp">181.56dp</dimen>
	<dimen name="_167sdp">182.66dp</dimen>
	<dimen name="_168sdp">183.75dp</dimen>
	<dimen name="_169sdp">184.84dp</dimen>
	<dimen name="_170sdp">185.94dp</dimen>
	<dimen name="_171sdp">187.03dp</dimen>
	<dimen name="_172sdp">188.13dp</dimen>
	<dimen name="_173sdp">189.22dp</dimen>
	<dimen name="_174sdp">190.31dp</dimen>
	<dimen name="_175sdp">191.41dp</dimen>
	<dimen name="_176sdp">192.50dp</dimen>
	<dimen name="_177sdp">193.59dp</dimen>
	<dimen name="_178sdp">194.69dp</dimen>
	<dimen name="_179sdp">195.78dp</dimen>
	<dimen name="_180sdp">196.88dp</dimen>
	<dimen name="_181sdp">197.97dp</dimen>
	<dimen name="_182sdp">199.06dp</dimen>
	<dimen name="_183sdp">200.16dp</dimen>
	<dimen name="_184sdp">201.25dp</dimen>
	<dimen name="_185sdp">202.34dp</dimen>
	<dimen name="_186sdp">203.44dp</dimen>
	<dimen name="_187sdp">204.53dp</dimen>
	<dimen name="_188sdp">205.63dp</dimen>
	<dimen name="_189sdp">206.72dp</dimen>
	<dimen name="_190sdp">207.81dp</dimen>
	<dimen name="_191sdp">208.91dp</dimen>
	<dimen name="_192sdp">210.00dp</dimen>
	<dimen name="_193sdp">211.09dp</dimen>
	<dimen name="_194sdp">212.19dp</dimen>
	<dimen name="_195sdp">213.28dp</dimen>
	<dimen name="_196sdp">214.38dp</dimen>
	<dimen name="_197sdp">215.47dp</dimen>
	<dimen name="_198sdp">216.56dp</dimen>
	<dimen name="_199sdp">217.66dp</dimen>
	<dimen name="_200sdp">218.75dp</dimen>
	<dimen name="_201sdp">219.84dp</dimen>
	<dimen name="_202sdp">220.94dp</dimen>
	<dimen name="_203sdp">222.03dp</dimen>
	<dimen name="_204sdp">223.12dp</dimen>
	<dimen name="_205sdp">224.22dp</dimen>
	<dimen name="_206sdp">225.31dp</dimen>
	<dimen name="_207sdp">226.41dp</dimen>
	<dimen name="_208sdp">227.50dp</dimen>
	<dimen name="_209sdp">228.59dp</dimen>
	<dimen name="_210sdp">229.69dp</dimen>
	<dimen name="_211sdp">230.78dp</dimen>
	<dimen name="_212sdp">231.88dp</dimen>
	<dimen name="_213sdp">232.97dp</dimen>
	<dimen name="_214sdp">234.06dp</dimen>
	<dimen name="_215sdp">235.16dp</dimen>
	<dimen name="_216sdp">236.25dp</dimen>
	<dimen name="_217sdp">237.34dp</dimen>
	<dimen name="_218sdp">238.44dp</dimen>
	<dimen name="_219sdp">239.53dp</dimen>
	<dimen name="_220sdp">240.63dp</dimen>
	<dimen name="_221sdp">241.72dp</dimen>
	<dimen name="_222sdp">242.81dp</dimen>
	<dimen name="_223sdp">243.91dp</dimen>
	<dimen name="_224sdp">245.00dp</dimen>
	<dimen name="_225sdp">246.09dp</dimen>
	<dimen name="_226sdp">247.19dp</dimen>
	<dimen name="_227sdp">248.28dp</dimen>
	<dimen name="_228sdp">249.38dp</dimen>
	<dimen name="_229sdp">250.47dp</dimen>
	<dimen name="_230sdp">251.56dp</dimen>
	<dimen name="_231sdp">252.66dp</dimen>
	<dimen name="_232sdp">253.75dp</dimen>
	<dimen name="_233sdp">254.84dp</dimen>
	<dimen name="_234sdp">255.94dp</dimen>
	<dimen name="_235sdp">257.03dp</dimen>
	<dimen name="_236sdp">258.13dp</dimen>
	<dimen name="_237sdp">259.22dp</dimen>
	<dimen name="_238sdp">260.31dp</dimen>
	<dimen name="_239sdp">261.41dp</dimen>
	<dimen name="_240sdp">262.50dp</dimen>
	<dimen name="_241sdp">263.59dp</dimen>
	<dimen name="_242sdp">264.69dp</dimen>
	<dimen name="_243sdp">265.78dp</dimen>
	<dimen name="_244sdp">266.88dp</dimen>
	<dimen name="_245sdp">267.97dp</dimen>
	<dimen name="_246sdp">269.06dp</dimen>
	<dimen name="_247sdp">270.16dp</dimen>
	<dimen name="_248sdp">271.25dp</dimen>
	<dimen name="_249sdp">272.34dp</dimen>
	<dimen name="_250sdp">273.44dp</dimen>
	<dimen name="_251sdp">274.53dp</dimen>
	<dimen name="_252sdp">275.63dp</dimen>
	<dimen name="_253sdp">276.72dp</dimen>
	<dimen name="_254sdp">277.81dp</dimen>
	<dimen name="_255sdp">278.91dp</dimen>
	<dimen name="_256sdp">280.00dp</dimen>
	<dimen name="_257sdp">281.09dp</dimen>
	<dimen name="_258sdp">282.19dp</dimen>
	<dimen name="_259sdp">283.28dp</dimen>
	<dimen name="_260sdp">284.38dp</dimen>
	<dimen name="_261sdp">285.47dp</dimen>
	<dimen name="_262sdp">286.56dp</dimen>
	<dimen name="_263sdp">287.66dp</dimen>
	<dimen name="_264sdp">288.75dp</dimen>
	<dimen name="_265sdp">289.84dp</dimen>
	<dimen name="_266sdp">290.94dp</dimen>
	<dimen name="_267sdp">292.03dp</dimen>
	<dimen name="_268sdp">293.13dp</dimen>
	<dimen name="_269sdp">294.22dp</dimen>
	<dimen name="_270sdp">295.31dp</dimen>
	<dimen name="_271sdp">296.41dp</dimen>
	<dimen name="_272sdp">297.50dp</dimen>
	<dimen name="_273sdp">298.59dp</dimen>
	<dimen name="_274sdp">299.69dp</dimen>
	<dimen name="_275sdp">300.78dp</dimen>
	<dimen name="_276sdp">301.88dp</dimen>
	<dimen name="_277sdp">302.97dp</dimen>
	<dimen name="_278sdp">304.06dp</dimen>
	<dimen name="_279sdp">305.16dp</dimen>
	<dimen name="_280sdp">306.25dp</dimen>
	<dimen name="_281sdp">307.34dp</dimen>
	<dimen name="_282sdp">308.44dp</dimen>
	<dimen name="_283sdp">309.53dp</dimen>
	<dimen name="_284sdp">310.63dp</dimen>
	<dimen name="_285sdp">311.72dp</dimen>
	<dimen name="_286sdp">312.81dp</dimen>
	<dimen name="_287sdp">313.91dp</dimen>
	<dimen name="_288sdp">315.00dp</dimen>
	<dimen name="_289sdp">316.09dp</dimen>
	<dimen name="_290sdp">317.19dp</dimen>
	<dimen name="_291sdp">318.28dp</dimen>
	<dimen name="_292sdp">319.38dp</dimen>
	<dimen name="_293sdp">320.47dp</dimen>
	<dimen name="_294sdp">321.56dp</dimen>
	<dimen name="_295sdp">322.66dp</dimen>
	<dimen name="_296sdp">323.75dp</dimen>
	<dimen name="_297sdp">324.84dp</dimen>
	<dimen name="_298sdp">325.94dp</dimen>
	<dimen name="_299sdp">327.03dp</dimen>
	<dimen name="_300sdp">328.13dp</dimen>
	<dimen name="_301sdp">329.22dp</dimen>
	<dimen name="_302sdp">330.31dp</dimen>
	<dimen name="_303sdp">331.41dp</dimen>
	<dimen name="_304sdp">332.50dp</dimen>
	<dimen name="_305sdp">333.59dp</dimen>
	<dimen name="_306sdp">334.69dp</dimen>
	<dimen name="_307sdp">335.78dp</dimen>
	<dimen name="_308sdp">336.88dp</dimen>
	<dimen name="_309sdp">337.97dp</dimen>
	<dimen name="_310sdp">339.06dp</dimen>
	<dimen name="_311sdp">340.16dp</dimen>
	<dimen name="_312sdp">341.25dp</dimen>
	<dimen name="_313sdp">342.34dp</dimen>
	<dimen name="_314sdp">343.44dp</dimen>
	<dimen name="_315sdp">344.53dp</dimen>
	<dimen name="_316sdp">345.63dp</dimen>
	<dimen name="_317sdp">346.72dp</dimen>
	<dimen name="_318sdp">347.81dp</dimen>
	<dimen name="_319sdp">348.91dp</dimen>
	<dimen name="_320sdp">350.00dp</dimen>
	<dimen name="_321sdp">351.09dp</dimen>
	<dimen name="_322sdp">352.19dp</dimen>
	<dimen name="_323sdp">353.28dp</dimen>
	<dimen name="_324sdp">354.38dp</dimen>
	<dimen name="_325sdp">355.47dp</dimen>
	<dimen name="_326sdp">356.56dp</dimen>
	<dimen name="_327sdp">357.66dp</dimen>
	<dimen name="_328sdp">358.75dp</dimen>
	<dimen name="_329sdp">359.84dp</dimen>
	<dimen name="_330sdp">360.94dp</dimen>
	<dimen name="_331sdp">362.03dp</dimen>
	<dimen name="_332sdp">363.13dp</dimen>
	<dimen name="_333sdp">364.22dp</dimen>
	<dimen name="_334sdp">365.31dp</dimen>
	<dimen name="_335sdp">366.41dp</dimen>
	<dimen name="_336sdp">367.50dp</dimen>
	<dimen name="_337sdp">368.59dp</dimen>
	<dimen name="_338sdp">369.69dp</dimen>
	<dimen name="_339sdp">370.78dp</dimen>
	<dimen name="_340sdp">371.88dp</dimen>
	<dimen name="_341sdp">372.97dp</dimen>
	<dimen name="_342sdp">374.06dp</dimen>
	<dimen name="_343sdp">375.16dp</dimen>
	<dimen name="_344sdp">376.25dp</dimen>
	<dimen name="_345sdp">377.34dp</dimen>
	<dimen name="_346sdp">378.44dp</dimen>
	<dimen name="_347sdp">379.53dp</dimen>
	<dimen name="_348sdp">380.62dp</dimen>
	<dimen name="_349sdp">381.72dp</dimen>
	<dimen name="_350sdp">382.81dp</dimen>
	<dimen name="_351sdp">383.91dp</dimen>
	<dimen name="_352sdp">385.00dp</dimen>
	<dimen name="_353sdp">386.09dp</dimen>
	<dimen name="_354sdp">387.19dp</dimen>
	<dimen name="_355sdp">388.28dp</dimen>
	<dimen name="_356sdp">389.38dp</dimen>
	<dimen name="_357sdp">390.47dp</dimen>
	<dimen name="_358sdp">391.56dp</dimen>
	<dimen name="_359sdp">392.66dp</dimen>
	<dimen name="_360sdp">393.75dp</dimen>
	<dimen name="_361sdp">394.84dp</dimen>
	<dimen name="_362sdp">395.94dp</dimen>
	<dimen name="_363sdp">397.03dp</dimen>
	<dimen name="_364sdp">398.13dp</dimen>
	<dimen name="_365sdp">399.22dp</dimen>
	<dimen name="_366sdp">400.31dp</dimen>
	<dimen name="_367sdp">401.41dp</dimen>
	<dimen name="_368sdp">402.50dp</dimen>
	<dimen name="_369sdp">403.59dp</dimen>
	<dimen name="_370sdp">404.69dp</dimen>
	<dimen name="_371sdp">405.78dp</dimen>
	<dimen name="_372sdp">406.88dp</dimen>
	<dimen name="_373sdp">407.97dp</dimen>
	<dimen name="_374sdp">409.06dp</dimen>
	<dimen name="_375sdp">410.16dp</dimen>
	<dimen name="_376sdp">411.25dp</dimen>
	<dimen name="_377sdp">412.34dp</dimen>
	<dimen name="_378sdp">413.44dp</dimen>
	<dimen name="_379sdp">414.53dp</dimen>
	<dimen name="_380sdp">415.63dp</dimen>
	<dimen name="_381sdp">416.72dp</dimen>
	<dimen name="_382sdp">417.81dp</dimen>
	<dimen name="_383sdp">418.91dp</dimen>
	<dimen name="_384sdp">420.00dp</dimen>
	<dimen name="_385sdp">421.09dp</dimen>
	<dimen name="_386sdp">422.19dp</dimen>
	<dimen name="_387sdp">423.28dp</dimen>
	<dimen name="_388sdp">424.37dp</dimen>
	<dimen name="_389sdp">425.47dp</dimen>
	<dimen name="_390sdp">426.56dp</dimen>
	<dimen name="_391sdp">427.66dp</dimen>
	<dimen name="_392sdp">428.75dp</dimen>
	<dimen name="_393sdp">429.84dp</dimen>
	<dimen name="_394sdp">430.94dp</dimen>
	<dimen name="_395sdp">432.03dp</dimen>
	<dimen name="_396sdp">433.13dp</dimen>
	<dimen name="_397sdp">434.22dp</dimen>
	<dimen name="_398sdp">435.31dp</dimen>
	<dimen name="_399sdp">436.41dp</dimen>
	<dimen name="_400sdp">437.50dp</dimen>
	<dimen name="_401sdp">438.59dp</dimen>
	<dimen name="_402sdp">439.69dp</dimen>
	<dimen name="_403sdp">440.78dp</dimen>
	<dimen name="_404sdp">441.88dp</dimen>
	<dimen name="_405sdp">442.97dp</dimen>
	<dimen name="_406sdp">444.06dp</dimen>
	<dimen name="_407sdp">445.16dp</dimen>
	<dimen name="_408sdp">446.25dp</dimen>
	<dimen name="_409sdp">447.34dp</dimen>
	<dimen name="_410sdp">448.44dp</dimen>
	<dimen name="_411sdp">449.53dp</dimen>
	<dimen name="_412sdp">450.63dp</dimen>
	<dimen name="_413sdp">451.72dp</dimen>
	<dimen name="_414sdp">452.81dp</dimen>
	<dimen name="_415sdp">453.91dp</dimen>
	<dimen name="_416sdp">455.00dp</dimen>
	<dimen name="_417sdp">456.09dp</dimen>
	<dimen name="_418sdp">457.19dp</dimen>
	<dimen name="_419sdp">458.28dp</dimen>
	<dimen name="_420sdp">459.38dp</dimen>
	<dimen name="_421sdp">460.47dp</dimen>
	<dimen name="_422sdp">461.56dp</dimen>
	<dimen name="_423sdp">462.66dp</dimen>
	<dimen name="_424sdp">463.75dp</dimen>
	<dimen name="_425sdp">464.84dp</dimen>
	<dimen name="_426sdp">465.94dp</dimen>
	<dimen name="_427sdp">467.03dp</dimen>
	<dimen name="_428sdp">468.12dp</dimen>
	<dimen name="_429sdp">469.22dp</dimen>
	<dimen name="_430sdp">470.31dp</dimen>
	<dimen name="_431sdp">471.41dp</dimen>
	<dimen name="_432sdp">472.50dp</dimen>
	<dimen name="_433sdp">473.59dp</dimen>
	<dimen name="_434sdp">474.69dp</dimen>
	<dimen name="_435sdp">475.78dp</dimen>
	<dimen name="_436sdp">476.88dp</dimen>
	<dimen name="_437sdp">477.97dp</dimen>
	<dimen name="_438sdp">479.06dp</dimen>
	<dimen name="_439sdp">480.16dp</dimen>
	<dimen name="_440sdp">481.25dp</dimen>
	<dimen name="_441sdp">482.34dp</dimen>
	<dimen name="_442sdp">483.44dp</dimen>
	<dimen name="_443sdp">484.53dp</dimen>
	<dimen name="_444sdp">485.63dp</dimen>
	<dimen name="_445sdp">486.72dp</dimen>
	<dimen name="_446sdp">487.81dp</dimen>
	<dimen name="_447sdp">488.91dp</dimen>
	<dimen name="_448sdp">490.00dp</dimen>
	<dimen name="_449sdp">491.09dp</dimen>
	<dimen name="_450sdp">492.19dp</dimen>
	<dimen name="_451sdp">493.28dp</dimen>
	<dimen name="_452sdp">494.38dp</dimen>
	<dimen name="_453sdp">495.47dp</dimen>
	<dimen name="_454sdp">496.56dp</dimen>
	<dimen name="_455sdp">497.66dp</dimen>
	<dimen name="_456sdp">498.75dp</dimen>
	<dimen name="_457sdp">499.84dp</dimen>
	<dimen name="_458sdp">500.94dp</dimen>
	<dimen name="_459sdp">502.03dp</dimen>
	<dimen name="_460sdp">503.13dp</dimen>
	<dimen name="_461sdp">504.22dp</dimen>
	<dimen name="_462sdp">505.31dp</dimen>
	<dimen name="_463sdp">506.41dp</dimen>
	<dimen name="_464sdp">507.50dp</dimen>
	<dimen name="_465sdp">508.59dp</dimen>
	<dimen name="_466sdp">509.69dp</dimen>
	<dimen name="_467sdp">510.78dp</dimen>
	<dimen name="_468sdp">511.87dp</dimen>
	<dimen name="_469sdp">512.97dp</dimen>
	<dimen name="_470sdp">514.06dp</dimen>
	<dimen name="_471sdp">515.16dp</dimen>
	<dimen name="_472sdp">516.25dp</dimen>
	<dimen name="_473sdp">517.34dp</dimen>
	<dimen name="_474sdp">518.44dp</dimen>
	<dimen name="_475sdp">519.53dp</dimen>
	<dimen name="_476sdp">520.63dp</dimen>
	<dimen name="_477sdp">521.72dp</dimen>
	<dimen name="_478sdp">522.81dp</dimen>
	<dimen name="_479sdp">523.91dp</dimen>
	<dimen name="_480sdp">525.00dp</dimen>
	<dimen name="_481sdp">526.09dp</dimen>
	<dimen name="_482sdp">527.19dp</dimen>
	<dimen name="_483sdp">528.28dp</dimen>
	<dimen name="_484sdp">529.38dp</dimen>
	<dimen name="_485sdp">530.47dp</dimen>
	<dimen name="_486sdp">531.56dp</dimen>
	<dimen name="_487sdp">532.66dp</dimen>
	<dimen name="_488sdp">533.75dp</dimen>
	<dimen name="_489sdp">534.84dp</dimen>
	<dimen name="_490sdp">535.94dp</dimen>
	<dimen name="_491sdp">537.03dp</dimen>
	<dimen name="_492sdp">538.13dp</dimen>
	<dimen name="_493sdp">539.22dp</dimen>
	<dimen name="_494sdp">540.31dp</dimen>
	<dimen name="_495sdp">541.41dp</dimen>
	<dimen name="_496sdp">542.50dp</dimen>
	<dimen name="_497sdp">543.59dp</dimen>
	<dimen name="_498sdp">544.69dp</dimen>
	<dimen name="_499sdp">545.78dp</dimen>
	<dimen name="_500sdp">546.88dp</dimen>
	<dimen name="_501sdp">547.97dp</dimen>
	<dimen name="_502sdp">549.06dp</dimen>
	<dimen name="_503sdp">550.16dp</dimen>
	<dimen name="_504sdp">551.25dp</dimen>
	<dimen name="_505sdp">552.34dp</dimen>
	<dimen name="_506sdp">553.44dp</dimen>
	<dimen name="_507sdp">554.53dp</dimen>
	<dimen name="_508sdp">555.63dp</dimen>
	<dimen name="_509sdp">556.72dp</dimen>
	<dimen name="_510sdp">557.81dp</dimen>
	<dimen name="_511sdp">558.91dp</dimen>
	<dimen name="_512sdp">560.00dp</dimen>
	<dimen name="_513sdp">561.09dp</dimen>
	<dimen name="_514sdp">562.19dp</dimen>
	<dimen name="_515sdp">563.28dp</dimen>
	<dimen name="_516sdp">564.38dp</dimen>
	<dimen name="_517sdp">565.47dp</dimen>
	<dimen name="_518sdp">566.56dp</dimen>
	<dimen name="_519sdp">567.66dp</dimen>
	<dimen name="_520sdp">568.75dp</dimen>
	<dimen name="_521sdp">569.84dp</dimen>
	<dimen name="_522sdp">570.94dp</dimen>
	<dimen name="_523sdp">572.03dp</dimen>
	<dimen name="_524sdp">573.13dp</dimen>
	<dimen name="_525sdp">574.22dp</dimen>
	<dimen name="_526sdp">575.31dp</dimen>
	<dimen name="_527sdp">576.41dp</dimen>
	<dimen name="_528sdp">577.50dp</dimen>
	<dimen name="_529sdp">578.59dp</dimen>
	<dimen name="_530sdp">579.69dp</dimen>
	<dimen name="_531sdp">580.78dp</dimen>
	<dimen name="_532sdp">581.88dp</dimen>
	<dimen name="_533sdp">582.97dp</dimen>
	<dimen name="_534sdp">584.06dp</dimen>
	<dimen name="_535sdp">585.16dp</dimen>
	<dimen name="_536sdp">586.25dp</dimen>
	<dimen name="_537sdp">587.34dp</dimen>
	<dimen name="_538sdp">588.44dp</dimen>
	<dimen name="_539sdp">589.53dp</dimen>
	<dimen name="_540sdp">590.63dp</dimen>
	<dimen name="_541sdp">591.72dp</dimen>
	<dimen name="_542sdp">592.81dp</dimen>
	<dimen name="_543sdp">593.91dp</dimen>
	<dimen name="_544sdp">595.00dp</dimen>
	<dimen name="_545sdp">596.09dp</dimen>
	<dimen name="_546sdp">597.19dp</dimen>
	<dimen name="_547sdp">598.28dp</dimen>
	<dimen name="_548sdp">599.38dp</dimen>
	<dimen name="_549sdp">600.47dp</dimen>
	<dimen name="_550sdp">601.56dp</dimen>
	<dimen name="_551sdp">602.66dp</dimen>
	<dimen name="_552sdp">603.75dp</dimen>
	<dimen name="_553sdp">604.84dp</dimen>
	<dimen name="_554sdp">605.94dp</dimen>
	<dimen name="_555sdp">607.03dp</dimen>
	<dimen name="_556sdp">608.13dp</dimen>
	<dimen name="_557sdp">609.22dp</dimen>
	<dimen name="_558sdp">610.31dp</dimen>
	<dimen name="_559sdp">611.41dp</dimen>
	<dimen name="_560sdp">612.50dp</dimen>
	<dimen name="_561sdp">613.59dp</dimen>
	<dimen name="_562sdp">614.69dp</dimen>
	<dimen name="_563sdp">615.78dp</dimen>
	<dimen name="_564sdp">616.88dp</dimen>
	<dimen name="_565sdp">617.97dp</dimen>
	<dimen name="_566sdp">619.06dp</dimen>
	<dimen name="_567sdp">620.16dp</dimen>
	<dimen name="_568sdp">621.25dp</dimen>
	<dimen name="_569sdp">622.34dp</dimen>
	<dimen name="_570sdp">623.44dp</dimen>
	<dimen name="_571sdp">624.53dp</dimen>
	<dimen name="_572sdp">625.63dp</dimen>
	<dimen name="_573sdp">626.72dp</dimen>
	<dimen name="_574sdp">627.81dp</dimen>
	<dimen name="_575sdp">628.91dp</dimen>
	<dimen name="_576sdp">630.00dp</dimen>
	<dimen name="_577sdp">631.09dp</dimen>
	<dimen name="_578sdp">632.19dp</dimen>
	<dimen name="_579sdp">633.28dp</dimen>
	<dimen name="_580sdp">634.38dp</dimen>
	<dimen name="_581sdp">635.47dp</dimen>
	<dimen name="_582sdp">636.56dp</dimen>
	<dimen name="_583sdp">637.66dp</dimen>
	<dimen name="_584sdp">638.75dp</dimen>
	<dimen name="_585sdp">639.84dp</dimen>
	<dimen name="_586sdp">640.94dp</dimen>
	<dimen name="_587sdp">642.03dp</dimen>
	<dimen name="_588sdp">643.13dp</dimen>
	<dimen name="_589sdp">644.22dp</dimen>
	<dimen name="_590sdp">645.31dp</dimen>
	<dimen name="_591sdp">646.41dp</dimen>
	<dimen name="_592sdp">647.50dp</dimen>
	<dimen name="_593sdp">648.59dp</dimen>
	<dimen name="_594sdp">649.69dp</dimen>
	<dimen name="_595sdp">650.78dp</dimen>
	<dimen name="_596sdp">651.88dp</dimen>
	<dimen name="_597sdp">652.97dp</dimen>
	<dimen name="_598sdp">654.06dp</dimen>
	<dimen name="_599sdp">655.16dp</dimen>
	<dimen name="_600sdp">656.25dp</dimen>
</resources>
